data_go_mcp/__init__.py
data_go_mcp/apartment_trade/__init__.py
data_go_mcp/apartment_trade/api_client.py
data_go_mcp/apartment_trade/models.py
data_go_mcp/apartment_trade/server.py
data_go_mcp_apartment_trade-1.0.1.dist-info/METADATA
data_go_mcp_apartment_trade-1.0.1.dist-info/WHEEL
data_go_mcp_apartment_trade-1.0.1.dist-info/entry_points.txt
data_go_mcp_apartment_trade-1.0.1.dist-info/RECORD
