Metadata-Version: 2.4
Name: data-go-mcp.apartment-trade
Version: 1.0.1
Summary: MCP server for Korea apartment trade data from data.go.kr
Project-URL: Homepage, https://github.com/Koomook/data-go-mcp-servers
Project-URL: Repository, https://github.com/Koomook/data-go-mcp-servers
Project-URL: Issues, https://github.com/Koomook/data-go-mcp-servers/issues
Author: Data.go.kr MCP Servers Contributors
License: Apache-2.0
Keywords: apartment,api,data.go.kr,korea,mcp,real-estate
Classifier: Development Status :: 3 - Alpha
Classifier: Intended Audience :: Developers
Classifier: License :: OSI Approved :: Apache Software License
Classifier: Programming Language :: Python :: 3
Classifier: Programming Language :: Python :: 3.10
Classifier: Programming Language :: Python :: 3.11
Classifier: Programming Language :: Python :: 3.12
Requires-Python: >=3.10
Requires-Dist: httpx>=0.27.0
Requires-Dist: mcp>=1.0.0
Requires-Dist: pydantic>=2.0.0
Requires-Dist: xmltodict>=0.14.0
Provides-Extra: dev
Requires-Dist: pytest-asyncio>=0.24.0; extra == 'dev'
Requires-Dist: pytest-httpx>=0.30.0; extra == 'dev'
Requires-Dist: pytest>=8.0.0; extra == 'dev'
